{
	"id": "default",
	"name": "theme_default",
	"description": "標準の青・緑・オレンジ・赤・紫・ティール・グレー",
	"version": 1,
	"builtIn": true,
	"ui": {
		"primary": {
			"50": "#eff6ff",
			"100": "#dbeafe",
			"200": "#bfdbfe",
			"300": "#93c5fd",
			"400": "#60a5fa",
			"500": "#3b82f6",
			"600": "#2563eb",
			"700": "#1d4ed8",
			"800": "#1e40af",
			"900": "#1e3a8a"
		},
		"surface": {
			"page": "#f9fafb",
			"card": "#ffffff",
			"border": "#e5e7eb",
			"muted": "#f3f4f6",
			"mutedForeground": "#6b7280"
		},
		"nav": {
			"bg": "#ffffff",
			"active": "#2563eb",
			"inactive": "#9ca3af",
			"hover": "#f3f4f6"
		},
		"shadow": {
			"sheet": "0 -4px 16px rgba(0,0,0,0.08)",
			"card": "0 1px 3px rgba(0,0,0,0.06), 0 1px 2px rgba(0,0,0,0.04)",
			"modal": "0 20px 25px -5px rgba(0,0,0,0.1), 0 8px 10px -6px rgba(0,0,0,0.04)"
		},
		"radius": {
			"pill": "9999px",
			"card": "16px",
			"chip": "8px"
		},
		"secondary": {
			"50": "#f0fdfa",
			"100": "#ccfbf1",
			"200": "#99f6e4",
			"300": "#5eead4",
			"400": "#2dd4bf",
			"500": "#14b8a6",
			"600": "#0d9488",
			"700": "#0f766e",
			"800": "#115e59",
			"900": "#134e4a"
		},
		"success": {
			"50": "#f0fdf4",
			"100": "#dcfce7",
			"200": "#bbf7d0",
			"300": "#86efac",
			"400": "#4ade80",
			"500": "#22c55e",
			"600": "#16a34a",
			"700": "#15803d",
			"800": "#166534",
			"900": "#14532d"
		},
		"warning": {
			"50": "#fffbeb",
			"100": "#fef3c7",
			"200": "#fde68a",
			"300": "#fcd34d",
			"400": "#fbbf24",
			"500": "#f59e0b",
			"600": "#d97706",
			"700": "#b45309",
			"800": "#92400e",
			"900": "#78350f"
		},
		"danger": {
			"50": "#fef2f2",
			"100": "#fee2e2",
			"200": "#fecaca",
			"300": "#fca5a5",
			"400": "#f87171",
			"500": "#ef4444",
			"600": "#dc2626",
			"700": "#b91c1c",
			"800": "#991b1b",
			"900": "#7f1d1d"
		}
	},
	"palette": {
		"courseColors": [
			{
				"id": "blue",
				"name": "color_blue",
				"hex": "#3b82f6"
			},
			{
				"id": "green",
				"name": "color_green",
				"hex": "#22c55e"
			},
			{
				"id": "orange",
				"name": "color_orange",
				"hex": "#f97316"
			},
			{
				"id": "red",
				"name": "color_red",
				"hex": "#ef4444"
			},
			{
				"id": "purple",
				"name": "color_purple",
				"hex": "#a855f7"
			},
			{
				"id": "teal",
				"name": "color_teal",
				"hex": "#14b8a6"
			},
			{
				"id": "gray",
				"name": "color_gray",
				"hex": "#6b7280"
			}
		],
		"todoColors": [
			{
				"id": "blue",
				"name": "color_blue",
				"hex": "#3b82f6"
			},
			{
				"id": "green",
				"name": "color_green",
				"hex": "#22c55e"
			},
			{
				"id": "orange",
				"name": "color_orange",
				"hex": "#f97316"
			},
			{
				"id": "red",
				"name": "color_red",
				"hex": "#ef4444"
			},
			{
				"id": "purple",
				"name": "color_purple",
				"hex": "#a855f7"
			},
			{
				"id": "teal",
				"name": "color_teal",
				"hex": "#14b8a6"
			}
		],
		"eventColors": [
			{
				"id": "blue",
				"name": "color_blue",
				"hex": "#3b82f6"
			},
			{
				"id": "green",
				"name": "color_green",
				"hex": "#22c55e"
			},
			{
				"id": "orange",
				"name": "color_orange",
				"hex": "#f97316"
			},
			{
				"id": "red",
				"name": "color_red",
				"hex": "#ef4444"
			},
			{
				"id": "purple",
				"name": "color_purple",
				"hex": "#a855f7"
			},
			{
				"id": "teal",
				"name": "color_teal",
				"hex": "#14b8a6"
			},
			{
				"id": "pink",
				"name": "color_pink",
				"hex": "#ec4899"
			},
			{
				"id": "indigo",
				"name": "color_indigo",
				"hex": "#6366f1"
			},
			{
				"id": "amber",
				"name": "color_amber",
				"hex": "#f59e0b"
			},
			{
				"id": "gray",
				"name": "color_gray",
				"hex": "#6b7280"
			}
		]
	},
	"attendance": {
		"present": {
			"fg": "#ffffff",
			"bg": "#22c55e"
		},
		"absent": {
			"fg": "#ffffff",
			"bg": "#ef4444"
		},
		"late": {
			"fg": "#ffffff",
			"bg": "#f97316"
		},
		"excused": {
			"fg": "#ffffff",
			"bg": "#3b82f6"
		},
		"cancelled": {
			"fg": "#ffffff",
			"bg": "#6b7280"
		}
	}
}
